acdh_baserow_pyutils/__init__.py
acdh_baserow_pyutils-0.11.0.dist-info/WHEEL
acdh_baserow_pyutils-0.11.0.dist-info/METADATA
acdh_baserow_pyutils-0.11.0.dist-info/RECORD
