Metadata-Version: 2.3
Name: acdh-baserow-pyutils
Version: 0.11.0
Summary: API client for Baserow
Keywords: Baserow,api client
Author: Peter Andorfer, Daniel Elsner
Author-email: Peter Andorfer <peter.andorfer@oeaw.ac.at>, Daniel Elsner <daniel.elsner@oeaw.ac.at>
License: MIT License
Requires-Dist: requests>=2.32.5
Requires-Python: >=3.9
Project-URL: Documentation, https://acdh-oeaw.github.io/acdh-baserow-pyutils/
Project-URL: Repository, https://github.com/acdh-oeaw/acdh-baserow-pyutils
